plugins/gdscript.yaml
plugins/python.yaml
plugins/yaml.yaml
reveal/__init__.py
reveal/base.py
reveal/config.py
reveal/defaults.py
reveal/elements.py
reveal/main.py
reveal/registry.py
reveal/structure.py
reveal/structure_options.py
reveal/tree_view.py
reveal/treesitter.py
reveal/type_system.py
reveal/adapters/__init__.py
reveal/adapters/ast.py
reveal/adapters/base.py
reveal/adapters/diff.py
reveal/adapters/env.py
reveal/adapters/help.py
reveal/adapters/imports.py
reveal/adapters/json_adapter.py
reveal/adapters/markdown.py
reveal/adapters/mysql.py
reveal/adapters/reveal.py
reveal/adapters/stats.py
reveal/adapters/claude/__init__.py
reveal/adapters/claude/adapter.py
reveal/adapters/claude/renderer.py
reveal/adapters/claude/analysis/__init__.py
reveal/adapters/claude/analysis/errors.py
reveal/adapters/claude/analysis/messages.py
reveal/adapters/claude/analysis/overview.py
reveal/adapters/claude/analysis/timeline.py
reveal/adapters/claude/analysis/tools.py
reveal/adapters/git/__init__.py
reveal/adapters/git/adapter.py
reveal/adapters/help_data/__init__.py
reveal/adapters/help_data/diff.yaml
reveal/adapters/help_data/mysql.yaml
reveal/adapters/help_data/sqlite.yaml
reveal/adapters/help_data/ssl.yaml
reveal/adapters/help_data/stats.yaml
reveal/adapters/mysql/__init__.py
reveal/adapters/mysql/adapter.py
reveal/adapters/mysql/connection.py
reveal/adapters/mysql/health.py
reveal/adapters/mysql/performance.py
reveal/adapters/mysql/renderer.py
reveal/adapters/mysql/replication.py
reveal/adapters/mysql/storage.py
reveal/adapters/python/__init__.py
reveal/adapters/python/adapter.py
reveal/adapters/python/bytecode.py
reveal/adapters/python/doctor.py
reveal/adapters/python/help.py
reveal/adapters/python/modules.py
reveal/adapters/python/packages.py
reveal/adapters/python/renderer.py
reveal/adapters/sqlite/__init__.py
reveal/adapters/sqlite/adapter.py
reveal/adapters/sqlite/renderer.py
reveal/adapters/ssl/__init__.py
reveal/adapters/ssl/adapter.py
reveal/adapters/ssl/certificate.py
reveal_cli-0.44.2.dist-info/licenses/LICENSE
reveal_cli-0.44.2.dist-info/METADATA
reveal_cli-0.44.2.dist-info/WHEEL
reveal_cli-0.44.2.dist-info/entry_points.txt
reveal_cli-0.44.2.dist-info/top_level.txt
reveal_cli-0.44.2.dist-info/RECORD
